bokehmol/.bokeh
bokehmol/.npmignore
bokehmol/__init__.py
bokehmol/_version.py
bokehmol/bokeh.ext.json
bokehmol/config.py
bokehmol/hover.py
bokehmol/index.ts
bokehmol/package-lock.json
bokehmol/package.json
bokehmol/tsconfig.json
bokehmol/utils.py
bokehmol/models/__init__.py
bokehmol/models/base_formatter.py
bokehmol/models/base_formatter.ts
bokehmol/models/base_hover.py
bokehmol/models/base_hover.ts
bokehmol/models/combinesvg.ts
bokehmol/models/index.ts
bokehmol/models/rdkit_formatter.py
bokehmol/models/rdkit_formatter.ts
bokehmol/models/rdkit_hover.py
bokehmol/models/rdkit_hover.ts
bokehmol/models/smilesdrawer_formatter.py
bokehmol/models/smilesdrawer_formatter.ts
bokehmol/models/smilesdrawer_hover.py
bokehmol/models/smilesdrawer_hover.ts
bokehmol/dist/bokehmol.js
bokehmol/dist/bokehmol.js.map
bokehmol/dist/bokehmol.json
bokehmol/dist/bokehmol.min.js
bokehmol/dist/lib/index.d.ts
bokehmol/dist/lib/index.d.ts.map
bokehmol/dist/lib/index.js
bokehmol/dist/lib/index.js.map
bokehmol/dist/lib/models/base_formatter.d.ts
bokehmol/dist/lib/models/base_formatter.d.ts.map
bokehmol/dist/lib/models/base_formatter.js
bokehmol/dist/lib/models/base_formatter.js.map
bokehmol/dist/lib/models/base_hover.d.ts
bokehmol/dist/lib/models/base_hover.d.ts.map
bokehmol/dist/lib/models/base_hover.js
bokehmol/dist/lib/models/base_hover.js.map
bokehmol/dist/lib/models/combinesvg.d.ts
bokehmol/dist/lib/models/combinesvg.d.ts.map
bokehmol/dist/lib/models/combinesvg.js
bokehmol/dist/lib/models/combinesvg.js.map
bokehmol/dist/lib/models/index.d.ts
bokehmol/dist/lib/models/index.d.ts.map
bokehmol/dist/lib/models/index.js
bokehmol/dist/lib/models/index.js.map
bokehmol/dist/lib/models/rdkit_formatter.d.ts
bokehmol/dist/lib/models/rdkit_formatter.d.ts.map
bokehmol/dist/lib/models/rdkit_formatter.js
bokehmol/dist/lib/models/rdkit_formatter.js.map
bokehmol/dist/lib/models/rdkit_hover.d.ts
bokehmol/dist/lib/models/rdkit_hover.d.ts.map
bokehmol/dist/lib/models/rdkit_hover.js
bokehmol-0.2.0.dist-info/METADATA
bokehmol-0.2.0.dist-info/WHEEL
bokehmol-0.2.0.dist-info/licenses/LICENSE
bokehmol-0.2.0.dist-info/RECORD
