Metadata-Version: 2.4
Name: bokehmol
Version: 0.2.0
Summary: Tools for plotting molecules in Bokeh
Project-URL: Homepage, https://github.com/cbouy/bokehmol
Project-URL: Documentation, https://nbviewer.org/github/cbouy/bokehmol/blob/master/notebooks/quickstart.ipynb
Project-URL: Discussions, https://github.com/cbouy/bokehmol/discussions
Project-URL: Issues, https://github.com/cbouy/bokehmol/issues
Project-URL: Changelog, https://github.com/cbouy/bokehmol/blob/master/CHANGELOG.md
Author-email: Cédric Bouysset <cedric@bouysset.net>
License:                                  Apache License
License-File: LICENSE
Keywords: cheminformatics,chemistry,chemoinformatics,drug-design,science
Classifier: Development Status :: 3 - Alpha
Classifier: Intended Audience :: Science/Research
Classifier: Operating System :: OS Independent
Classifier: Programming Language :: Python :: 3
Classifier: Programming Language :: Python :: 3.10
Classifier: Programming Language :: Python :: 3.11
Classifier: Programming Language :: Python :: 3.12
Classifier: Topic :: Scientific/Engineering :: Chemistry
Requires-Python: >=3.10
Requires-Dist: bokeh<4,>=3.6.0
